xRedUtils/__init__.py
xRedUtils/colors.py
xRedUtils/dates.py
xRedUtils/dicts.py
xRedUtils/errors.py
xRedUtils/files.py
xRedUtils/funcs.py
xRedUtils/general.py
xRedUtils/generators.py
xRedUtils/hashing.py
xRedUtils/iterables.py
xRedUtils/maths.py
xRedUtils/objects.py
xRedUtils/paths.py
xRedUtils/regexes.py
xRedUtils/strings.py
xRedUtils/system.py
xRedUtils/times.py
xRedUtils/type_converters.py
xRedUtils/type_hints.py
xRedUtils/modules/reloader.py
xRedUtilsAsync/__init__.py
xRedUtilsAsync/colors.py
xRedUtilsAsync/dates.py
xRedUtilsAsync/dicts.py
xRedUtilsAsync/errors.py
xRedUtilsAsync/files.py
xRedUtilsAsync/funcs.py
xRedUtilsAsync/general.py
xRedUtilsAsync/generators.py
xRedUtilsAsync/hashing.py
xRedUtilsAsync/iterables.py
xRedUtilsAsync/maths.py
xRedUtilsAsync/objects.py
xRedUtilsAsync/paths.py
xRedUtilsAsync/regexes.py
xRedUtilsAsync/strings.py
xRedUtilsAsync/system.py
xRedUtilsAsync/times.py
xRedUtilsAsync/type_converters.py
xRedUtilsAsync/type_hints.py
xRedUtilsAsync/modules/reloader.py
xRedUtilsTests/async_test.py
xRedUtilsTests/file_test.txt
xRedUtilsTests/sync_test.py
xRedUtilsTests/loaders/dates.py
xRedUtilsTests/loaders/dicts.py
xRedUtilsTests/loaders/errors.py
xRedUtilsTests/loaders/funcs.py
xRedUtilsTests/loaders/general.py
xRedUtilsTests/loaders/generators.py
xRedUtilsTests/loaders/hashing.py
xRedUtilsTests/loaders/iterables.py
xRedUtilsTests/loaders/maths.py
xRedUtilsTests/loaders/objects.py
xRedUtilsTests/loaders/paths.py
xRedUtilsTests/loaders/strings.py
xRedUtilsTests/loaders/times.py
xRedUtilsTests/loaders/type_converters.py
xRedUtils-2.3.2.dist-info/LICENSE
xRedUtils-2.3.2.dist-info/METADATA
xRedUtils-2.3.2.dist-info/WHEEL
xRedUtils-2.3.2.dist-info/top_level.txt
xRedUtils-2.3.2.dist-info/RECORD
