Metadata-Version: 2.1
Name: xRedUtils
Version: 2.3.2
Summary: Simple, general purpose functions in one place!
Author: xRedCrystalx
Project-URL: Homepage, https://github.com/xRedCrystalx/xRedUtils
Project-URL: Issues, https://github.com/xRedCrystalx/xRedUtils/issues
Classifier: Natural Language :: English
Classifier: Intended Audience :: Developers
Classifier: Programming Language :: Python :: 3.12
Classifier: Operating System :: OS Independent
Classifier: Typing :: Typed
Classifier: Topic :: Utilities
Requires-Python: >=3.12
License-File: LICENSE
